subsparser/__init__.py
subsparser/constants.py
subsparser/subtitle.py
subsparser/times.py
subsparser/readers/__init__.py
subsparser/readers/base.py
subsparser/readers/srt.py
subsparser/readers/txt.py
subsparser-0.0.6.dist-info/LICENSE
subsparser-0.0.6.dist-info/METADATA
subsparser-0.0.6.dist-info/WHEEL
subsparser-0.0.6.dist-info/top_level.txt
subsparser-0.0.6.dist-info/RECORD
